{
  "ticker": "سغدير",
  "industry": "سيمان، آهك و گچ",
  "timeframe": "1W",
  "metadata": {
    "return_type": "log_return",
    "calendar": "jalali"
  },
  "metrics": {
    "annualized_expected_return": 0.20848910078677793,
    "annualized_volatility": 0.3087094350873729,
    "coverage": {
      "weeks_available": 219,
      "first_week": "1400-09-20",
      "last_week": "1404-11-25"
    },
    "liquidity": {
      "average_weekly_volume": 9609168.972222222,
      "average_weekly_trade_value_toman": 7976458889.032406,
      "median_weekly_trade_value_toman": 2853472124.95
    },
    "risk": {
      "max_drawdown": -0.34360010098459987
    }
  },
  "data": [
    {
      "week_start_date": "1400-09-20",
      "week_end_date": "1400-09-24",
      "open": 4123.0,
      "high": 4612.0,
      "low": 4123.0,
      "close": 4463.0,
      "weekly_volume": 281020280.0,
      "weekly_trade_value_toman": 120187442311.4,
      "simple_return": null,
      "log_return": null,
      "rolling_26w_volatility": null
    },
    {
      "week_start_date": "1400-09-27",
      "week_end_date": "1400-10-01",
      "open": 4481.0,
      "high": 4519.0,
      "low": 4004.0,
      "close": 4398.0,
      "weekly_volume": 29900939.0,
      "weekly_trade_value_toman": 12600555206.999998,
      "simple_return": -0.014564194488012548,
      "log_return": -0.01467129351456336,
      "rolling_26w_volatility": null
    },
    {
      "week_start_date": "1400-10-04",
      "week_end_date": "1400-10-08",
      "open": 4442.0,
      "high": 4504.0,
      "low": 4208.0,
      "close": 4252.0,
      "weekly_volume": 12159734.0,
      "weekly_trade_value_toman": 5355756723.7,
      "simple_return": -0.03319690768531151,
      "log_return": -0.03376043165286791,
      "rolling_26w_volatility": null
    },
    {
      "week_start_date": "1400-10-11",
      "week_end_date": "1400-10-15",
      "open": 4353.0,
      "high": 4379.0,
      "low": 4066.0,
      "close": 4208.0,
      "weekly_volume": 4850002.0,
      "weekly_trade_value_toman": 2056996677.7,
      "simple_return": -0.010348071495766699,
      "log_return": -0.010401985044292725,
      "rolling_26w_volatility": null
    },
    {
      "week_start_date": "1400-10-18",
      "week_end_date": "1400-10-22",
      "open": 4186.0,
      "high": 4282.0,
      "low": 4018.0,
      "close": 4214.0,
      "weekly_volume": 3200763.0,
      "weekly_trade_value_toman": 1317626327.9,
      "simple_return": 0.0014258555133079848,
      "log_return": 0.0014248399465885526,
      "rolling_26w_volatility": null
    },
    {
      "week_start_date": "1400-10-25",
      "week_end_date": "1400-10-29",
      "open": 4153.0,
      "high": 4180.0,
      "low": 3957.0,
      "close": 4069.0,
      "weekly_volume": 1388241.0,
      "weekly_trade_value_toman": 564083953.8,
      "simple_return": -0.03440911248220219,
      "log_return": -0.03501504636244434,
      "rolling_26w_volatility": null
    },
    {
      "week_start_date": "1400-11-02",
      "week_end_date": "1400-11-06",
      "open": 4196.0,
      "high": 4196.0,
      "low": 3858.0,
      "close": 4038.0,
      "weekly_volume": 2541475.0,
      "weekly_trade_value_toman": 1014283719.9000001,
      "simple_return": -0.007618579503563529,
      "log_return": -0.007647749128907101,
      "rolling_26w_volatility": null
    },
    {
      "week_start_date": "1400-11-09",
      "week_end_date": "1400-11-13",
      "open": 4035.0,
      "high": 4057.0,
      "low": 3874.0,
      "close": 3908.0,
      "weekly_volume": 1973168.0,
      "weekly_trade_value_toman": 785588743.4,
      "simple_return": -0.032194155522535906,
      "log_return": -0.03272378571010944,
      "rolling_26w_volatility": null
    },
    {
      "week_start_date": "1400-11-16",
      "week_end_date": "1400-11-20",
      "open": 3988.0,
      "high": 3988.0,
      "low": 3648.0,
      "close": 3762.0,
      "weekly_volume": 2177498.0,
      "weekly_trade_value_toman": 820145623.6999999,
      "simple_return": -0.03735926305015353,
      "log_return": -0.03807500330169771,
      "rolling_26w_volatility": null
    },
    {
      "week_start_date": "1400-11-23",
      "week_end_date": "1400-11-27",
      "open": 3769.0,
      "high": 3871.0,
      "low": 3679.0,
      "close": 3800.0,
      "weekly_volume": 916348.0,
      "weekly_trade_value_toman": 348527496.5,
      "simple_return": 0.010101010101010102,
      "log_return": 0.010050335853501506,
      "rolling_26w_volatility": null
    },
    {
      "week_start_date": "1400-11-30",
      "week_end_date": "1400-12-04",
      "open": 3806.0,
      "high": 4007.0,
      "low": 3800.0,
      "close": 3967.0,
      "weekly_volume": 818944.0,
      "weekly_trade_value_toman": 321002103.2,
      "simple_return": 0.04394736842105263,
      "log_return": 0.0430090747998531,
      "rolling_26w_volatility": null
    },
    {
      "week_start_date": "1400-12-07",
      "week_end_date": "1400-12-11",
      "open": 3874.0,
      "high": 3985.0,
      "low": 3670.0,
      "close": 3840.0,
      "weekly_volume": 633635.0,
      "weekly_trade_value_toman": 245791254.9,
      "simple_return": -0.032014116460801614,
      "log_return": -0.03253777493255764,
      "rolling_26w_volatility": null
    },
    {
      "week_start_date": "1400-12-14",
      "week_end_date": "1400-12-18",
      "open": 3775.0,
      "high": 3945.0,
      "low": 3769.0,
      "close": 3852.0,
      "weekly_volume": 832097.0,
      "weekly_trade_value_toman": 322035493.20000005,
      "simple_return": 0.003125,
      "log_return": 0.0031201273362436777,
      "rolling_26w_volatility": null
    },
    {
      "week_start_date": "1400-12-21",
      "week_end_date": "1400-12-25",
      "open": 3775.0,
      "high": 3914.0,
      "low": 3468.0,
      "close": 3626.0,
      "weekly_volume": 4039957.0,
      "weekly_trade_value_toman": 1453823452.2,
      "simple_return": -0.05867082035306334,
      "log_return": -0.06046238160321984,
      "rolling_26w_volatility": null
    },
    {
      "week_start_date": "1400-12-28",
      "week_end_date": "1401-01-03",
      "open": 3592.0,
      "high": 3685.0,
      "low": 3552.0,
      "close": 3592.0,
      "weekly_volume": 262533.0,
      "weekly_trade_value_toman": 94301853.6,
      "simple_return": -0.009376723662437948,
      "log_return": -0.009420961892706107,
      "rolling_26w_volatility": null
    },
    {
      "week_start_date": "1401-01-06",
      "week_end_date": "1401-01-10",
      "open": 3608.0,
      "high": 3775.0,
      "low": 3499.0,
      "close": 3728.0,
      "weekly_volume": 26688306.0,
      "weekly_trade_value_toman": 9691493355.9,
      "simple_return": 0.0378619153674833,
      "log_return": 0.03716274638339157,
      "rolling_26w_volatility": null
    },
    {
      "week_start_date": "1401-01-13",
      "week_end_date": "1401-01-17",
      "open": 3713.0,
      "high": 3725.0,
      "low": 3555.0,
      "close": 3589.0,
      "weekly_volume": 3675067.0,
      "weekly_trade_value_toman": 1351200420.4,
      "simple_return": -0.037285407725321885,
      "log_return": -0.0379982846578745,
      "rolling_26w_volatility": null
    },
    {
      "week_start_date": "1401-01-20",
      "week_end_date": "1401-01-24",
      "open": 3651.0,
      "high": 3688.0,
      "low": 3496.0,
      "close": 3533.0,
      "weekly_volume": 5498414.0,
      "weekly_trade_value_toman": 1972459976.4,
      "simple_return": -0.01560323209807746,
      "log_return": -0.015726243788462047,
      "rolling_26w_volatility": null
    },
    {
      "week_start_date": "1401-01-27",
      "week_end_date": "1401-01-31",
      "open": 3515.0,
      "high": 3927.0,
      "low": 3453.0,
      "close": 3673.0,
      "weekly_volume": 17859229.0,
      "weekly_trade_value_toman": 6603927167.099999,
      "simple_return": 0.03962637984715539,
      "log_return": 0.03886139846052215,
      "rolling_26w_volatility": null
    },
    {
      "week_start_date": "1401-02-03",
      "week_end_date": "1401-02-07",
      "open": 3738.0,
      "high": 3787.0,
      "low": 3570.0,
      "close": 3623.0,
      "weekly_volume": 4409664.0,
      "weekly_trade_value_toman": 1610993279.8000002,
      "simple_return": -0.013612850530901171,
      "log_return": -0.01370635492459013,
      "rolling_26w_volatility": null
    },
    {
      "week_start_date": "1401-02-10",
      "week_end_date": "1401-02-14",
      "open": 3716.0,
      "high": 3747.0,
      "low": 3580.0,
      "close": 3731.0,
      "weekly_volume": 2897299.0,
      "weekly_trade_value_toman": 1063625956.4,
      "simple_return": 0.029809550096605023,
      "log_return": 0.02937388232608072,
      "rolling_26w_volatility": null
    },
    {
      "week_start_date": "1401-02-17",
      "week_end_date": "1401-02-21",
      "open": 3747.0,
      "high": 4041.0,
      "low": 3694.0,
      "close": 4007.0,
      "weekly_volume": 9361920.0,
      "weekly_trade_value_toman": 3628944581.6,
      "simple_return": 0.07397480568212275,
      "log_return": 0.07136653741498673,
      "rolling_26w_volatility": null
    },
    {
      "week_start_date": "1401-02-24",
      "week_end_date": "1401-02-28",
      "open": 4137.0,
      "high": 4428.0,
      "low": 4063.0,
      "close": 4295.0,
      "weekly_volume": 8734646.0,
      "weekly_trade_value_toman": 3694378661.7000003,
      "simple_return": 0.0718742201147991,
      "log_return": 0.06940872378221113,
      "rolling_26w_volatility": null
    },
    {
      "week_start_date": "1401-02-31",
      "week_end_date": "1401-03-04",
      "open": 4301.0,
      "high": 4428.0,
      "low": 3995.0,
      "close": 4075.0,
      "weekly_volume": 3923924.0,
      "weekly_trade_value_toman": 1625709033.1,
      "simple_return": -0.051222351571594875,
      "log_return": -0.05258080874339261,
      "rolling_26w_volatility": null
    },
    {
      "week_start_date": "1401-03-07",
      "week_end_date": "1401-03-11",
      "open": 4100.0,
      "high": 4177.0,
      "low": 3936.0,
      "close": 4078.0,
      "weekly_volume": 8299269.0,
      "weekly_trade_value_toman": 3384135331.2,
      "simple_return": 0.000736196319018405,
      "log_return": 0.0007359254594374421,
      "rolling_26w_volatility": null
    },
    {
      "week_start_date": "1401-03-14",
      "week_end_date": "1401-03-18",
      "open": 4078.0,
      "high": 4317.0,
      "low": 4075.0,
      "close": 4143.0,
      "weekly_volume": 1227921.0,
      "weekly_trade_value_toman": 506248087.6,
      "simple_return": 0.015939185875429134,
      "log_return": 0.01581349094300139,
      "rolling_26w_volatility": null
    },
    {
      "week_start_date": "1401-03-21",
      "week_end_date": "1401-03-25",
      "open": 4180.0,
      "high": 4707.0,
      "low": 4180.0,
      "close": 4614.0,
      "weekly_volume": 3550546.0,
      "weekly_trade_value_toman": 1585374362.1,
      "simple_return": 0.11368573497465605,
      "log_return": 0.10767499665629718,
      "rolling_26w_volatility": 0.29607561573837826
    },
    {
      "week_start_date": "1401-03-28",
      "week_end_date": "1401-04-01",
      "open": 4561.0,
      "high": 4886.0,
      "low": 4555.0,
      "close": 4704.0,
      "weekly_volume": 12929099.0,
      "weekly_trade_value_toman": 6181296862.2,
      "simple_return": 0.01950585175552666,
      "log_return": 0.019318050844763877,
      "rolling_26w_volatility": 0.2961687191300262
    },
    {
      "week_start_date": "1401-04-04",
      "week_end_date": "1401-04-08",
      "open": 4886.0,
      "high": 4893.0,
      "low": 4496.0,
      "close": 4543.0,
      "weekly_volume": 6655329.0,
      "weekly_trade_value_toman": 3163275572.2000003,
      "simple_return": -0.03422619047619048,
      "log_return": -0.034825623819059535,
      "rolling_26w_volatility": 0.29644433272078835
    },
    {
      "week_start_date": "1401-04-11",
      "week_end_date": "1401-04-15",
      "open": 4456.0,
      "high": 4642.0,
      "low": 4283.0,
      "close": 4283.0,
      "weekly_volume": 1518645.0,
      "weekly_trade_value_toman": 672407238.6999999,
      "simple_return": -0.05723090468853181,
      "log_return": -0.05893388814403227,
      "rolling_26w_volatility": 0.3085515419327349
    },
    {
      "week_start_date": "1401-04-18",
      "week_end_date": "1401-04-22",
      "open": 4258.0,
      "high": 4338.0,
      "low": 4193.0,
      "close": 4252.0,
      "weekly_volume": 521759.0,
      "weekly_trade_value_toman": 221993267.7,
      "simple_return": -0.007237917347653514,
      "log_return": -0.0072642381535324724,
      "rolling_26w_volatility": 0.30875250869722143
    },
    {
      "week_start_date": "1401-04-25",
      "week_end_date": "1401-04-29",
      "open": 4400.0,
      "high": 4540.0,
      "low": 4196.0,
      "close": 4496.0,
      "weekly_volume": 1657784.0,
      "weekly_trade_value_toman": 732795735.8,
      "simple_return": 0.05738476011288805,
      "log_return": 0.05579865211168847,
      "rolling_26w_volatility": 0.3137893702160503
    },
    {
      "week_start_date": "1401-05-01",
      "week_end_date": "1401-05-05",
      "open": 4620.0,
      "high": 4620.0,
      "low": 4382.0,
      "close": 4481.0,
      "weekly_volume": 1167872.0,
      "weekly_trade_value_toman": 521113270.5,
      "simple_return": -0.0033362989323843417,
      "log_return": -0.003341876787383931,
      "rolling_26w_volatility": 0.3135205101898066
    },
    {
      "week_start_date": "1401-05-08",
      "week_end_date": "1401-05-12",
      "open": 4490.0,
      "high": 4583.0,
      "low": 4385.0,
      "close": 4441.0,
      "weekly_volume": 910465.0,
      "weekly_trade_value_toman": 406528223.20000005,
      "simple_return": -0.00892657888864093,
      "log_return": -0.008966659494040729,
      "rolling_26w_volatility": 0.30950629406213387
    },
    {
      "week_start_date": "1401-05-15",
      "week_end_date": "1401-05-19",
      "open": 4444.0,
      "high": 4561.0,
      "low": 4233.0,
      "close": 4242.0,
      "weekly_volume": 592053.0,
      "weekly_trade_value_toman": 254952819.59999996,
      "simple_return": -0.0448097275388426,
      "log_return": -0.04584472016747451,
      "rolling_26w_volatility": 0.3119366702866369
    },
    {
      "week_start_date": "1401-05-22",
      "week_end_date": "1401-05-26",
      "open": 4233.0,
      "high": 4382.0,
      "low": 4165.0,
      "close": 4273.0,
      "weekly_volume": 817333.0,
      "weekly_trade_value_toman": 350580285.2,
      "simple_return": 0.007307873644507308,
      "log_return": 0.0072813005193972415,
      "rolling_26w_volatility": 0.3118609504805254
    },
    {
      "week_start_date": "1401-05-29",
      "week_end_date": "1401-06-02",
      "open": 4369.0,
      "high": 4369.0,
      "low": 4119.0,
      "close": 4258.0,
      "weekly_volume": 2351588.0,
      "weekly_trade_value_toman": 1013160958.4,
      "simple_return": -0.0035104142288790077,
      "log_return": -0.0035165901906001507,
      "rolling_26w_volatility": 0.30681519861334644
    },
    {
      "week_start_date": "1401-06-05",
      "week_end_date": "1401-06-09",
      "open": 4258.0,
      "high": 4289.0,
      "low": 4168.0,
      "close": 4177.0,
      "weekly_volume": 478565.0,
      "weekly_trade_value_toman": 202683519.10000002,
      "simple_return": -0.01902301550023485,
      "log_return": -0.019206280956249478,
      "rolling_26w_volatility": 0.3041965055856757
    },
    {
      "week_start_date": "1401-06-12",
      "week_end_date": "1401-06-16",
      "open": 4165.0,
      "high": 4304.0,
      "low": 4134.0,
      "close": 4218.0,
      "weekly_volume": 260543.0,
      "weekly_trade_value_toman": 110535084.39999999,
      "simple_return": 0.009815657170217859,
      "log_return": 0.009767796541544638,
      "rolling_26w_volatility": 0.30433650567267734
    },
    {
      "week_start_date": "1401-06-19",
      "week_end_date": "1401-06-23",
      "open": 4140.0,
      "high": 4258.0,
      "low": 4057.0,
      "close": 4134.0,
      "weekly_volume": 160585.0,
      "weekly_trade_value_toman": 66975391.8,
      "simple_return": -0.01991465149359886,
      "log_return": -0.020115620797006305,
      "rolling_26w_volatility": 0.29179156455417943
    },
    {
      "week_start_date": "1401-06-26",
      "week_end_date": "1401-06-30",
      "open": 4109.0,
      "high": 4363.0,
      "low": 4106.0,
      "close": 4252.0,
      "weekly_volume": 5239588.0,
      "weekly_trade_value_toman": 2227449993.9,
      "simple_return": 0.028543783260764392,
      "log_return": 0.028143999220125036,
      "rolling_26w_volatility": 0.2927529656810879
    },
    {
      "week_start_date": "1401-07-02",
      "week_end_date": "1401-07-06",
      "open": 4069.0,
      "high": 4533.0,
      "low": 4069.0,
      "close": 4472.0,
      "weekly_volume": 4106253.0,
      "weekly_trade_value_toman": 1814208067.6,
      "simple_return": 0.05174035747883349,
      "log_return": 0.050446275373096594,
      "rolling_26w_volatility": 0.2962301302981834
    },
    {
      "week_start_date": "1401-07-09",
      "week_end_date": "1401-07-13",
      "open": 4348.0,
      "high": 4558.0,
      "low": 4329.0,
      "close": 4459.0,
      "weekly_volume": 1862383.0,
      "weekly_trade_value_toman": 837335864.6,
      "simple_return": -0.0029069767441860465,
      "log_return": -0.0029112102074584415,
      "rolling_26w_volatility": 0.2892173036433449
    },
    {
      "week_start_date": "1401-07-16",
      "week_end_date": "1401-07-20",
      "open": 4506.0,
      "high": 4555.0,
      "low": 4397.0,
      "close": 4527.0,
      "weekly_volume": 4335708.0,
      "weekly_trade_value_toman": 1950279295.1999998,
      "simple_return": 0.015250056066382597,
      "log_return": 0.015134942808481974,
      "rolling_26w_volatility": 0.28715979443720235
    },
    {
      "week_start_date": "1401-07-23",
      "week_end_date": "1401-07-27",
      "open": 4459.0,
      "high": 4598.0,
      "low": 4459.0,
      "close": 4521.0,
      "weekly_volume": 2079805.0,
      "weekly_trade_value_toman": 946243368.5,
      "simple_return": -0.0013253810470510272,
      "log_return": -0.0013262601413534553,
      "rolling_26w_volatility": 0.2842323876845363
    },
    {
      "week_start_date": "1401-07-30",
      "week_end_date": "1401-08-04",
      "open": 4521.0,
      "high": 4552.0,
      "low": 4403.0,
      "close": 4403.0,
      "weekly_volume": 4752332.0,
      "weekly_trade_value_toman": 2137925324.7,
      "simple_return": -0.026100420261004204,
      "log_return": -0.02644708153885135,
      "rolling_26w_volatility": 0.2868145888908109
    },
    {
      "week_start_date": "1401-08-07",
      "week_end_date": "1401-08-11",
      "open": 4410.0,
      "high": 4456.0,
      "low": 4338.0,
      "close": 4366.0,
      "weekly_volume": 360976.0,
      "weekly_trade_value_toman": 157574351.29999998,
      "simple_return": -0.008403361344537815,
      "log_return": -0.008438868645864595,
      "rolling_26w_volatility": 0.28579946399498046
    },
    {
      "week_start_date": "1401-08-14",
      "week_end_date": "1401-08-18",
      "open": 4462.0,
      "high": 4496.0,
      "low": 4295.0,
      "close": 4304.0,
      "weekly_volume": 724322.0,
      "weekly_trade_value_toman": 319324750.70000005,
      "simple_return": -0.014200641319285386,
      "log_return": -0.014302435268268807,
      "rolling_26w_volatility": 0.27033351981329257
    },
    {
      "week_start_date": "1401-08-21",
      "week_end_date": "1401-08-25",
      "open": 4289.0,
      "high": 4332.0,
      "low": 4174.0,
      "close": 4211.0,
      "weekly_volume": 1333692.0,
      "weekly_trade_value_toman": 570104459.8000001,
      "simple_return": -0.021607806691449814,
      "log_return": -0.02184467367969255,
      "rolling_26w_volatility": 0.2538306767100952
    },
    {
      "week_start_date": "1401-08-28",
      "week_end_date": "1401-09-02",
      "open": 4317.0,
      "high": 4317.0,
      "low": 4149.0,
      "close": 4211.0,
      "weekly_volume": 687103.0,
      "weekly_trade_value_toman": 287796771.9,
      "simple_return": 0.0,
      "log_return": 0.0,
      "rolling_26w_volatility": 0.24212463339683982
    },
    {
      "week_start_date": "1401-09-05",
      "week_end_date": "1401-09-09",
      "open": 4211.0,
      "high": 4258.0,
      "low": 4149.0,
      "close": 4165.0,
      "weekly_volume": 72737.0,
      "weekly_trade_value_toman": 30446229.0,
      "simple_return": -0.010923771075753978,
      "log_return": -0.01098387356098466,
      "rolling_26w_volatility": 0.24274415860716084
    },
    {
      "week_start_date": "1401-09-12",
      "week_end_date": "1401-09-16",
      "open": 4149.0,
      "high": 4267.0,
      "low": 4088.0,
      "close": 4106.0,
      "weekly_volume": 192869.0,
      "weekly_trade_value_toman": 80192385.30000001,
      "simple_return": -0.014165666266506602,
      "log_return": -0.014266957022064198,
      "rolling_26w_volatility": 0.24260497765210334
    },
    {
      "week_start_date": "1401-09-19",
      "week_end_date": "1401-09-23",
      "open": 4088.0,
      "high": 4311.0,
      "low": 4078.0,
      "close": 4236.0,
      "weekly_volume": 1173211.0,
      "weekly_trade_value_toman": 487813156.2,
      "simple_return": 0.031660983925962005,
      "log_return": 0.03117010914241825,
      "rolling_26w_volatility": 0.1902227128041472
    },
    {
      "week_start_date": "1401-09-26",
      "week_end_date": "1401-09-30",
      "open": 4295.0,
      "high": 4354.0,
      "low": 4106.0,
      "close": 4332.0,
      "weekly_volume": 3334693.0,
      "weekly_trade_value_toman": 1428133970.1999998,
      "simple_return": 0.0226628895184136,
      "log_return": 0.02240990139958411,
      "rolling_26w_volatility": 0.1910354802796393
    },
    {
      "week_start_date": "1401-10-03",
      "week_end_date": "1401-10-07",
      "open": 4403.0,
      "high": 4769.0,
      "low": 4289.0,
      "close": 4586.0,
      "weekly_volume": 8996863.0,
      "weekly_trade_value_toman": 4130220411.7,
      "simple_return": 0.05863342566943675,
      "log_return": 0.056978855296968514,
      "rolling_26w_volatility": 0.20312719229594095
    },
    {
      "week_start_date": "1401-10-10",
      "week_end_date": "1401-10-14",
      "open": 4586.0,
      "high": 4586.0,
      "low": 4586.0,
      "close": 4586.0,
      "weekly_volume": 0.0,
      "weekly_trade_value_toman": 0.0,
      "simple_return": 0.0,
      "log_return": 0.0,
      "rolling_26w_volatility": 0.1834930696435627
    },
    {
      "week_start_date": "1401-10-17",
      "week_end_date": "1401-10-21",
      "open": 4743.0,
      "high": 5039.0,
      "low": 4730.0,
      "close": 4824.0,
      "weekly_volume": 41964383.0,
      "weekly_trade_value_toman": 20541964768.8,
      "simple_return": 0.051897078063672046,
      "log_return": 0.05059527498917163,
      "rolling_26w_volatility": 0.19489456121032186
    },
    {
      "week_start_date": "1401-10-24",
      "week_end_date": "1401-10-28",
      "open": 4730.0,
      "high": 4945.0,
      "low": 4555.0,
      "close": 4723.0,
      "weekly_volume": 8212641.0,
      "weekly_trade_value_toman": 3898292240.5,
      "simple_return": -0.02093698175787728,
      "log_return": -0.02115926851090426,
      "rolling_26w_volatility": 0.18308299514097542
    },
    {
      "week_start_date": "1401-11-01",
      "week_end_date": "1401-11-05",
      "open": 4891.0,
      "high": 4905.0,
      "low": 4474.0,
      "close": 4568.0,
      "weekly_volume": 8949554.0,
      "weekly_trade_value_toman": 4191231015.8999996,
      "simple_return": -0.03281812407368198,
      "log_return": -0.033368718560270995,
      "rolling_26w_volatility": 0.18967521098362278
    },
    {
      "week_start_date": "1401-11-08",
      "week_end_date": "1401-11-12",
      "open": 4508.0,
      "high": 4508.0,
      "low": 4191.0,
      "close": 4339.0,
      "weekly_volume": 5638498.0,
      "weekly_trade_value_toman": 2493227641.4,
      "simple_return": -0.05013134851138354,
      "log_return": -0.05143156553749547,
      "rolling_26w_volatility": 0.20321877210583283
    },
    {
      "week_start_date": "1401-11-15",
      "week_end_date": "1401-11-19",
      "open": 4420.0,
      "high": 4420.0,
      "low": 4010.0,
      "close": 4151.0,
      "weekly_volume": 4297301.0,
      "weekly_trade_value_toman": 1772974609.1000001,
      "simple_return": -0.04332795575017285,
      "log_return": -0.04429463774531199,
      "rolling_26w_volatility": 0.20251620953638796
    },
    {
      "week_start_date": "1401-11-22",
      "week_end_date": "1401-11-26",
      "open": 4064.0,
      "high": 4232.0,
      "low": 3942.0,
      "close": 4037.0,
      "weekly_volume": 2688768.0,
      "weekly_trade_value_toman": 1101483065.9,
      "simple_return": -0.027463261864610938,
      "log_return": -0.027847427200097905,
      "rolling_26w_volatility": 0.20565730638291888
    },
    {
      "week_start_date": "1401-11-29",
      "week_end_date": "1401-12-03",
      "open": 3976.0,
      "high": 4387.0,
      "low": 3916.0,
      "close": 4158.0,
      "weekly_volume": 4076601.0,
      "weekly_trade_value_toman": 1716982277.6999998,
      "simple_return": 0.02997275204359673,
      "log_return": 0.029532347565017523,
      "rolling_26w_volatility": 0.21046696479541982
    },
    {
      "week_start_date": "1401-12-06",
      "week_end_date": "1401-12-10",
      "open": 4070.0,
      "high": 4575.0,
      "low": 4070.0,
      "close": 4205.0,
      "weekly_volume": 17271786.0,
      "weekly_trade_value_toman": 7457233088.3,
      "simple_return": 0.011303511303511303,
      "log_return": 0.011240103989090262,
      "rolling_26w_volatility": 0.2093644429417367
    },
    {
      "week_start_date": "1401-12-13",
      "week_end_date": "1401-12-17",
      "open": 4346.0,
      "high": 4521.0,
      "low": 4178.0,
      "close": 4521.0,
      "weekly_volume": 6781042.0,
      "weekly_trade_value_toman": 3016317562.5,
      "simple_return": 0.0751486325802616,
      "log_return": 0.07245891488755664,
      "rolling_26w_volatility": 0.23275352036036065
    },
    {
      "week_start_date": "1401-12-20",
      "week_end_date": "1401-12-24",
      "open": 4615.0,
      "high": 4723.0,
      "low": 4313.0,
      "close": 4548.0,
      "weekly_volume": 7203611.0,
      "weekly_trade_value_toman": 3220274167.7,
      "simple_return": 0.005972130059721301,
      "log_return": 0.00595436757582151,
      "rolling_26w_volatility": 0.2303531260965872
    },
    {
      "week_start_date": "1401-12-27",
      "week_end_date": "1402-01-02",
      "open": 4575.0,
      "high": 4925.0,
      "low": 4575.0,
      "close": 4911.0,
      "weekly_volume": 15203058.0,
      "weekly_trade_value_toman": 7258029909.3,
      "simple_return": 0.07981530343007916,
      "log_return": 0.07679001116881803,
      "rolling_26w_volatility": 0.2504955076656531
    },
    {
      "week_start_date": "1402-01-05",
      "week_end_date": "1402-01-09",
      "open": 4790.0,
      "high": 5100.0,
      "low": 4635.0,
      "close": 4797.0,
      "weekly_volume": 7900720.0,
      "weekly_trade_value_toman": 3792133943.9,
      "simple_return": -0.023213194868662187,
      "log_return": -0.02348686453718062,
      "rolling_26w_volatility": 0.24468209854433512
    },
    {
      "week_start_date": "1402-01-12",
      "week_end_date": "1402-01-16",
      "open": 4878.0,
      "high": 5073.0,
      "low": 4736.0,
      "close": 5073.0,
      "weekly_volume": 13244027.0,
      "weekly_trade_value_toman": 6630772952.5,
      "simple_return": 0.05753595997498437,
      "log_return": 0.055941636064625995,
      "rolling_26w_volatility": 0.2557797641822247
    },
    {
      "week_start_date": "1402-01-19",
      "week_end_date": "1402-01-23",
      "open": 5248.0,
      "high": 6042.0,
      "low": 5167.0,
      "close": 6008.0,
      "weekly_volume": 68906744.0,
      "weekly_trade_value_toman": 38847304492.0,
      "simple_return": 0.18430908732505422,
      "log_return": 0.16915955587728063,
      "rolling_26w_volatility": 0.3455268282088298
    },
    {
      "week_start_date": "1402-01-26",
      "week_end_date": "1402-01-30",
      "open": 6055.0,
      "high": 6452.0,
      "low": 5853.0,
      "close": 6237.0,
      "weekly_volume": 38475113.0,
      "weekly_trade_value_toman": 23562560719.0,
      "simple_return": 0.038115845539280956,
      "log_return": 0.03740738308215192,
      "rolling_26w_volatility": 0.3470181780696811
    },
    {
      "week_start_date": "1402-02-02",
      "week_end_date": "1402-02-06",
      "open": 6190.0,
      "high": 6654.0,
      "low": 6169.0,
      "close": 6270.0,
      "weekly_volume": 14529934.0,
      "weekly_trade_value_toman": 9197297426.6,
      "simple_return": 0.005291005291005291,
      "log_return": 0.005277057100843819,
      "rolling_26w_volatility": 0.3425068353556419
    },
    {
      "week_start_date": "1402-02-09",
      "week_end_date": "1402-02-13",
      "open": 6270.0,
      "high": 6930.0,
      "low": 6264.0,
      "close": 6761.0,
      "weekly_volume": 19549973.0,
      "weekly_trade_value_toman": 12956108282.4,
      "simple_return": 0.07830940988835726,
      "log_return": 0.07539445346371147,
      "rolling_26w_volatility": 0.3516851937725172
    },
    {
      "week_start_date": "1402-02-16",
      "week_end_date": "1402-02-20",
      "open": 7057.0,
      "high": 7091.0,
      "low": 6331.0,
      "close": 6351.0,
      "weekly_volume": 14834736.0,
      "weekly_trade_value_toman": 10056349076.9,
      "simple_return": -0.06064191687620175,
      "log_return": -0.0625585272877031,
      "rolling_26w_volatility": 0.3668616737938523
    },
    {
      "week_start_date": "1402-02-23",
      "week_end_date": "1402-02-27",
      "open": 6237.0,
      "high": 6768.0,
      "low": 6095.0,
      "close": 6499.0,
      "weekly_volume": 5390124.0,
      "weekly_trade_value_toman": 3459676940.5,
      "simple_return": 0.023303416784758307,
      "log_return": 0.023036038091374063,
      "rolling_26w_volatility": 0.3629651520923603
    },
    {
      "week_start_date": "1402-02-30",
      "week_end_date": "1402-03-03",
      "open": 6344.0,
      "high": 6923.0,
      "low": 6190.0,
      "close": 6795.0,
      "weekly_volume": 3059190.0,
      "weekly_trade_value_toman": 2037924776.0,
      "simple_return": 0.045545468533620556,
      "log_return": 0.04453872869089517,
      "rolling_26w_volatility": 0.3641685027190201
    },
    {
      "week_start_date": "1402-03-06",
      "week_end_date": "1402-03-10",
      "open": 6970.0,
      "high": 7017.0,
      "low": 6391.0,
      "close": 7004.0,
      "weekly_volume": 5379431.0,
      "weekly_trade_value_toman": 3679429972.0,
      "simple_return": 0.030757910228108903,
      "log_return": 0.03029436682049829,
      "rolling_26w_volatility": 0.3619118483667078
    },
    {
      "week_start_date": "1402-03-13",
      "week_end_date": "1402-03-17",
      "open": 7253.0,
      "high": 7253.0,
      "low": 6916.0,
      "close": 7179.0,
      "weekly_volume": 2907846.0,
      "weekly_trade_value_toman": 2068124406.0,
      "simple_return": 0.024985722444317533,
      "log_return": 0.02467868317074053,
      "rolling_26w_volatility": 0.35841798667488
    },
    {
      "week_start_date": "1402-03-20",
      "week_end_date": "1402-03-24",
      "open": 7152.0,
      "high": 7253.0,
      "low": 6795.0,
      "close": 6990.0,
      "weekly_volume": 5036879.0,
      "weekly_trade_value_toman": 3531208757.7,
      "simple_return": -0.02632678646050982,
      "log_return": -0.02667954134862704,
      "rolling_26w_volatility": 0.3644540911509564
    },
    {
      "week_start_date": "1402-03-27",
      "week_end_date": "1402-03-31",
      "open": 7226.0,
      "high": 7367.0,
      "low": 6674.0,
      "close": 7360.0,
      "weekly_volume": 46429446.0,
      "weekly_trade_value_toman": 34035000664.9,
      "simple_return": 0.05293276108726753,
      "log_return": 0.05157937649506608,
      "rolling_26w_volatility": 0.367301312235433
    },
    {
      "week_start_date": "1402-04-03",
      "week_end_date": "1402-04-07",
      "open": 7454.0,
      "high": 7454.0,
      "low": 6445.0,
      "close": 6661.0,
      "weekly_volume": 27548903.0,
      "weekly_trade_value_toman": 18933321583.800003,
      "simple_return": -0.09497282608695652,
      "log_return": -0.09979030930974253,
      "rolling_26w_volatility": 0.40024851544489
    },
    {
      "week_start_date": "1402-04-10",
      "week_end_date": "1402-04-14",
      "open": 6755.0,
      "high": 6755.0,
      "low": 6304.0,
      "close": 6519.0,
      "weekly_volume": 5407188.0,
      "weekly_trade_value_toman": 3475034032.8,
      "simple_return": -0.02131812040234199,
      "log_return": -0.021548633488640157,
      "rolling_26w_volatility": 0.4030068053487314
    },
    {
      "week_start_date": "1402-04-17",
      "week_end_date": "1402-04-21",
      "open": 6580.0,
      "high": 6674.0,
      "low": 6169.0,
      "close": 6169.0,
      "weekly_volume": 7562121.0,
      "weekly_trade_value_toman": 4745748939.4,
      "simple_return": -0.053689216137444394,
      "log_return": -0.05518423971490067,
      "rolling_26w_volatility": 0.4104651662203247
    },
    {
      "week_start_date": "1402-04-24",
      "week_end_date": "1402-04-28",
      "open": 6190.0,
      "high": 6324.0,
      "low": 5698.0,
      "close": 5759.0,
      "weekly_volume": 3861338.0,
      "weekly_trade_value_toman": 2278732092.5,
      "simple_return": -0.06646133895282866,
      "log_return": -0.0687729017029663,
      "rolling_26w_volatility": 0.4231789301859613
    },
    {
      "week_start_date": "1402-04-31",
      "week_end_date": "1402-05-04",
      "open": 5712.0,
      "high": 6169.0,
      "low": 5678.0,
      "close": 5988.0,
      "weekly_volume": 1722394.0,
      "weekly_trade_value_toman": 1028322734.1999999,
      "simple_return": 0.039763847890258726,
      "log_return": 0.03899361803284654,
      "rolling_26w_volatility": 0.4209655410237504
    },
    {
      "week_start_date": "1402-05-07",
      "week_end_date": "1402-05-11",
      "open": 6055.0,
      "high": 6116.0,
      "low": 5685.0,
      "close": 5840.0,
      "weekly_volume": 3699626.0,
      "weekly_trade_value_toman": 2148627113.8,
      "simple_return": -0.024716098864395457,
      "log_return": -0.025026669717246184,
      "rolling_26w_volatility": 0.4145037795466465
    },
    {
      "week_start_date": "1402-05-14",
      "week_end_date": "1402-05-18",
      "open": 5988.0,
      "high": 6142.0,
      "low": 5712.0,
      "close": 5725.0,
      "weekly_volume": 5444590.0,
      "weekly_trade_value_toman": 3159394936.3,
      "simple_return": -0.019691780821917807,
      "log_return": -0.01988824739983234,
      "rolling_26w_volatility": 0.4090810868642015
    },
    {
      "week_start_date": "1402-05-21",
      "week_end_date": "1402-05-25",
      "open": 5974.0,
      "high": 6008.0,
      "low": 5450.0,
      "close": 5517.0,
      "weekly_volume": 3195338.0,
      "weekly_trade_value_toman": 1792142369.1999998,
      "simple_return": -0.03633187772925764,
      "log_return": -0.03700831515000958,
      "rolling_26w_volatility": 0.4111540482345926
    },
    {
      "week_start_date": "1402-05-28",
      "week_end_date": "1402-06-01",
      "open": 5631.0,
      "high": 5934.0,
      "low": 5402.0,
      "close": 5860.0,
      "weekly_volume": 2720091.0,
      "weekly_trade_value_toman": 1542437463.6999998,
      "simple_return": 0.06217147000181258,
      "log_return": 0.0603153692986275,
      "rolling_26w_volatility": 0.4161566405011795
    },
    {
      "week_start_date": "1402-06-04",
      "week_end_date": "1402-06-08",
      "open": 5941.0,
      "high": 5988.0,
      "low": 5550.0,
      "close": 5698.0,
      "weekly_volume": 3833655.0,
      "weekly_trade_value_toman": 2195103887.4,
      "simple_return": -0.02764505119453925,
      "log_return": -0.02803436751320464,
      "rolling_26w_volatility": 0.4202273164222002
    },
    {
      "week_start_date": "1402-06-11",
      "week_end_date": "1402-06-15",
      "open": 5591.0,
      "high": 6216.0,
      "low": 5591.0,
      "close": 6203.0,
      "weekly_volume": 7997582.0,
      "weekly_trade_value_toman": 4916521932.7,
      "simple_return": 0.08862758862758863,
      "log_return": 0.08491780991526397,
      "rolling_26w_volatility": 0.4243244458576684
    },
    {
      "week_start_date": "1402-06-18",
      "week_end_date": "1402-06-22",
      "open": 5988.0,
      "high": 6566.0,
      "low": 5914.0,
      "close": 6506.0,
      "weekly_volume": 5343340.0,
      "weekly_trade_value_toman": 3426050075.1000004,
      "simple_return": 0.04884733193615992,
      "log_return": 0.04769178206017929,
      "rolling_26w_volatility": 0.42714968771505574
    },
    {
      "week_start_date": "1402-06-25",
      "week_end_date": "1402-06-29",
      "open": 6526.0,
      "high": 6768.0,
      "low": 6250.0,
      "close": 6728.0,
      "weekly_volume": 4015754.0,
      "weekly_trade_value_toman": 2633765063.1,
      "simple_return": 0.03412234860129112,
      "log_return": 0.03355309461948725,
      "rolling_26w_volatility": 0.4181634926194754
    },
    {
      "week_start_date": "1402-07-01",
      "week_end_date": "1402-07-05",
      "open": 6889.0,
      "high": 6909.0,
      "low": 6324.0,
      "close": 6809.0,
      "weekly_volume": 5703876.0,
      "weekly_trade_value_toman": 3829838315.3,
      "simple_return": 0.012039239001189061,
      "log_return": 0.011967343830182577,
      "rolling_26w_volatility": 0.41487935933678005
    },
    {
      "week_start_date": "1402-07-08",
      "week_end_date": "1402-07-12",
      "open": 6903.0,
      "high": 6903.0,
      "low": 6142.0,
      "close": 6156.0,
      "weekly_volume": 8836015.0,
      "weekly_trade_value_toman": 5769207376.4,
      "simple_return": -0.0959024820091056,
      "log_return": -0.10081805052419676,
      "rolling_26w_volatility": 0.4399731037326737
    },
    {
      "week_start_date": "1402-07-15",
      "week_end_date": "1402-07-19",
      "open": 6122.0,
      "high": 6270.0,
      "low": 5920.0,
      "close": 6149.0,
      "weekly_volume": 2504929.0,
      "weekly_trade_value_toman": 1533404950.6999998,
      "simple_return": -0.0011371020142949967,
      "log_return": -0.001137749005300099,
      "rolling_26w_volatility": 0.3701514393682652
    },
    {
      "week_start_date": "1402-07-22",
      "week_end_date": "1402-07-26",
      "open": 5988.0,
      "high": 6250.0,
      "low": 5867.0,
      "close": 6116.0,
      "weekly_volume": 1847586.0,
      "weekly_trade_value_toman": 1135390039.7,
      "simple_return": -0.005366726296958855,
      "log_return": -0.0053811789045168186,
      "rolling_26w_volatility": 0.36629782241570746
    },
    {
      "week_start_date": "1402-07-29",
      "week_end_date": "1402-08-03",
      "open": 6156.0,
      "high": 6257.0,
      "low": 5826.0,
      "close": 5968.0,
      "weekly_volume": 786202.0,
      "weekly_trade_value_toman": 477613836.0,
      "simple_return": -0.02419882275997384,
      "log_return": -0.024496425165356172,
      "rolling_26w_volatility": 0.3676956408562399
    },
    {
      "week_start_date": "1402-08-06",
      "week_end_date": "1402-08-10",
      "open": 5840.0,
      "high": 6190.0,
      "low": 5705.0,
      "close": 6015.0,
      "weekly_volume": 1787584.0,
      "weekly_trade_value_toman": 1055819144.5,
      "simple_return": 0.007875335120643432,
      "log_return": 0.007844486525182574,
      "rolling_26w_volatility": 0.3501515600369948
    },
    {
      "week_start_date": "1402-08-13",
      "week_end_date": "1402-08-17",
      "open": 6270.0,
      "high": 6297.0,
      "low": 5826.0,
      "close": 6216.0,
      "weekly_volume": 6481618.0,
      "weekly_trade_value_toman": 4055606937.0,
      "simple_return": 0.03341645885286783,
      "log_return": 0.0328702636387041,
      "rolling_26w_volatility": 0.3431760832530506
    },
    {
      "week_start_date": "1402-08-20",
      "week_end_date": "1402-08-24",
      "open": 6136.0,
      "high": 6257.0,
      "low": 5961.0,
      "close": 6055.0,
      "weekly_volume": 2903896.0,
      "weekly_trade_value_toman": 1775401113.9,
      "simple_return": -0.0259009009009009,
      "log_return": -0.026242236060290757,
      "rolling_26w_volatility": 0.34312502600316236
    },
    {
      "week_start_date": "1402-08-27",
      "week_end_date": "1402-09-01",
      "open": 5988.0,
      "high": 6324.0,
      "low": 5947.0,
      "close": 6324.0,
      "weekly_volume": 2100911.0,
      "weekly_trade_value_toman": 1281832117.0,
      "simple_return": 0.044426094137076794,
      "log_return": 0.04346754234217009,
      "rolling_26w_volatility": 0.34282135221413884
    },
    {
      "week_start_date": "1402-09-04",
      "week_end_date": "1402-09-08",
      "open": 6391.0,
      "high": 6391.0,
      "low": 6075.0,
      "close": 6331.0,
      "weekly_volume": 4921529.0,
      "weekly_trade_value_toman": 3100845758.6,
      "simple_return": 0.0011068943706514865,
      "log_return": 0.0011062822147639938,
      "rolling_26w_volatility": 0.33943552500823093
    },
    {
      "week_start_date": "1402-09-11",
      "week_end_date": "1402-09-15",
      "open": 6163.0,
      "high": 6795.0,
      "low": 6163.0,
      "close": 6526.0,
      "weekly_volume": 11081237.0,
      "weekly_trade_value_toman": 7223117447.9,
      "simple_return": 0.030800821355236138,
      "log_return": 0.030335996609139472,
      "rolling_26w_volatility": 0.3405183222914359
    },
    {
      "week_start_date": "1402-09-18",
      "week_end_date": "1402-09-22",
      "open": 6553.0,
      "high": 6721.0,
      "low": 6452.0,
      "close": 6600.0,
      "weekly_volume": 7731228.0,
      "weekly_trade_value_toman": 5044923985.1,
      "simple_return": 0.011339258351210543,
      "log_return": 0.011275450861251073,
      "rolling_26w_volatility": 0.33941202391338515
    },
    {
      "week_start_date": "1402-09-25",
      "week_end_date": "1402-09-29",
      "open": 6492.0,
      "high": 6748.0,
      "low": 6445.0,
      "close": 6634.0,
      "weekly_volume": 7223855.0,
      "weekly_trade_value_toman": 4785445373.099999,
      "simple_return": 0.005151515151515152,
      "log_return": 0.005138291492480794,
      "rolling_26w_volatility": 0.33033710292947555
    },
    {
      "week_start_date": "1402-10-02",
      "week_end_date": "1402-10-06",
      "open": 6593.0,
      "high": 6795.0,
      "low": 6486.0,
      "close": 6593.0,
      "weekly_volume": 4872555.0,
      "weekly_trade_value_toman": 3205875821.1,
      "simple_return": -0.00618028338860416,
      "log_return": -0.006199460393698129,
      "rolling_26w_volatility": 0.29890479812494075
    },
    {
      "week_start_date": "1402-10-09",
      "week_end_date": "1402-10-13",
      "open": 6593.0,
      "high": 6661.0,
      "low": 6479.0,
      "close": 6620.0,
      "weekly_volume": 2283643.0,
      "weekly_trade_value_toman": 1500880052.0,
      "simple_return": 0.004095252540573335,
      "log_return": 0.004086889817754209,
      "rolling_26w_volatility": 0.2973255770255433
    },
    {
      "week_start_date": "1402-10-16",
      "week_end_date": "1402-10-20",
      "open": 6661.0,
      "high": 6896.0,
      "low": 6573.0,
      "close": 6795.0,
      "weekly_volume": 7881872.0,
      "weekly_trade_value_toman": 5310895800.2,
      "simple_return": 0.026435045317220542,
      "log_return": 0.026091677654190275,
      "rolling_26w_volatility": 0.2876732430484014
    },
    {
      "week_start_date": "1402-10-23",
      "week_end_date": "1402-10-27",
      "open": 6741.0,
      "high": 6903.0,
      "low": 6714.0,
      "close": 6842.0,
      "weekly_volume": 9455880.0,
      "weekly_trade_value_toman": 6438001316.7,
      "simple_return": 0.006916850625459897,
      "log_return": 0.006893038952305995,
      "rolling_26w_volatility": 0.26718681555490603
    },
    {
      "week_start_date": "1402-10-30",
      "week_end_date": "1402-11-04",
      "open": 6788.0,
      "high": 6842.0,
      "low": 6453.0,
      "close": 6659.0,
      "weekly_volume": 2686922.0,
      "weekly_trade_value_toman": 1812700233.4,
      "simple_return": -0.026746565331774334,
      "log_return": -0.027110763426927618,
      "rolling_26w_volatility": 0.2668855379965363
    },
    {
      "week_start_date": "1402-11-07",
      "week_end_date": "1402-11-11",
      "open": 6598.0,
      "high": 6918.0,
      "low": 6575.0,
      "close": 6781.0,
      "weekly_volume": 3303552.0,
      "weekly_trade_value_toman": 2224228910.8,
      "simple_return": 0.018321069229614056,
      "log_return": 0.01815526057321977,
      "rolling_26w_volatility": 0.26406004564760316
    },
    {
      "week_start_date": "1402-11-14",
      "week_end_date": "1402-11-18",
      "open": 6689.0,
      "high": 6788.0,
      "low": 6430.0,
      "close": 6750.0,
      "weekly_volume": 4299995.0,
      "weekly_trade_value_toman": 2909338118.2,
      "simple_return": -0.0045715971095708595,
      "log_return": -0.004582078817266643,
      "rolling_26w_volatility": 0.2618473683923726
    },
    {
      "week_start_date": "1402-11-21",
      "week_end_date": "1402-11-25",
      "open": 6582.0,
      "high": 6796.0,
      "low": 6582.0,
      "close": 6788.0,
      "weekly_volume": 2279947.0,
      "weekly_trade_value_toman": 1543689864.4999998,
      "simple_return": 0.005629629629629629,
      "log_return": 0.005613842487541448,
      "rolling_26w_volatility": 0.25399268756305965
    },
    {
      "week_start_date": "1402-11-28",
      "week_end_date": "1402-12-02",
      "open": 6643.0,
      "high": 6788.0,
      "low": 6506.0,
      "close": 6605.0,
      "weekly_volume": 2274455.0,
      "weekly_trade_value_toman": 1522515999.6,
      "simple_return": -0.026959340011785505,
      "log_return": -0.027329409397691195,
      "rolling_26w_volatility": 0.24655971039165517
    },
    {
      "week_start_date": "1402-12-05",
      "week_end_date": "1402-12-09",
      "open": 6598.0,
      "high": 6788.0,
      "low": 6399.0,
      "close": 6659.0,
      "weekly_volume": 418679.0,
      "weekly_trade_value_toman": 270825749.5,
      "simple_return": 0.00817562452687358,
      "log_return": 0.008142385154196685,
      "rolling_26w_volatility": 0.24186243896847254
    },
    {
      "week_start_date": "1402-12-12",
      "week_end_date": "1402-12-16",
      "open": 6560.0,
      "high": 6857.0,
      "low": 6483.0,
      "close": 6613.0,
      "weekly_volume": 2026639.0,
      "weekly_trade_value_toman": 1336619616.4,
      "simple_return": -0.00690794413575612,
      "log_return": -0.0069319144359600016,
      "rolling_26w_volatility": 0.21263572084181043
    },
    {
      "week_start_date": "1402-12-19",
      "week_end_date": "1402-12-23",
      "open": 6598.0,
      "high": 6773.0,
      "low": 6521.0,
      "close": 6560.0,
      "weekly_volume": 1451692.0,
      "weekly_trade_value_toman": 960063347.3,
      "simple_return": -0.008014516860728868,
      "log_return": -0.00804680573652763,
      "rolling_26w_volatility": 0.20233615155036191
    },
    {
      "week_start_date": "1402-12-26",
      "week_end_date": "1403-01-01",
      "open": 6598.0,
      "high": 6811.0,
      "low": 6521.0,
      "close": 6636.0,
      "weekly_volume": 805402.0,
      "weekly_trade_value_toman": 530286294.0,
      "simple_return": 0.011585365853658536,
      "log_return": 0.011518769372200284,
      "rolling_26w_volatility": 0.19714084244130245
    },
    {
      "week_start_date": "1403-01-04",
      "week_end_date": "1403-01-08",
      "open": 6865.0,
      "high": 6949.0,
      "low": 6628.0,
      "close": 6682.0,
      "weekly_volume": 3024932.0,
      "weekly_trade_value_toman": 2023992017.1999998,
      "simple_return": 0.006931886678722122,
      "log_return": 0.006907971606366635,
      "rolling_26w_volatility": 0.19660285875412498
    },
    {
      "week_start_date": "1403-01-11",
      "week_end_date": "1403-01-15",
      "open": 6857.0,
      "high": 6941.0,
      "low": 6674.0,
      "close": 6865.0,
      "weekly_volume": 750382.0,
      "weekly_trade_value_toman": 509540025.5,
      "simple_return": 0.02738700987728225,
      "log_return": 0.027018695285369484,
      "rolling_26w_volatility": 0.13456273278169706
    },
    {
      "week_start_date": "1403-01-18",
      "week_end_date": "1403-01-22",
      "open": 6712.0,
      "high": 7147.0,
      "low": 6697.0,
      "close": 6956.0,
      "weekly_volume": 1897666.0,
      "weekly_trade_value_toman": 1318018634.5,
      "simple_return": 0.01325564457392571,
      "log_return": 0.01316855727210232,
      "rolling_26w_volatility": 0.13490454185704215
    },
    {
      "week_start_date": "1403-01-25",
      "week_end_date": "1403-01-29",
      "open": 6895.0,
      "high": 6903.0,
      "low": 6712.0,
      "close": 6826.0,
      "weekly_volume": 4515518.0,
      "weekly_trade_value_toman": 3056137627.4,
      "simple_return": -0.01868890166762507,
      "log_return": -0.018865746007521274,
      "rolling_26w_volatility": 0.13831420833303146
    },
    {
      "week_start_date": "1403-02-01",
      "week_end_date": "1403-02-05",
      "open": 6826.0,
      "high": 7139.0,
      "low": 6598.0,
      "close": 6834.0,
      "weekly_volume": 5886642.0,
      "weekly_trade_value_toman": 4026088128.1,
      "simple_return": 0.0011719894520949312,
      "log_return": 0.001171303208584816,
      "rolling_26w_volatility": 0.1318398856816512
    },
    {
      "week_start_date": "1403-02-08",
      "week_end_date": "1403-02-12",
      "open": 6750.0,
      "high": 6865.0,
      "low": 6666.0,
      "close": 6674.0,
      "weekly_volume": 2983769.0,
      "weekly_trade_value_toman": 2005805136.1,
      "simple_return": -0.023412350014632717,
      "log_return": -0.023690773363917814,
      "rolling_26w_volatility": 0.1379321729944264
    },
    {
      "week_start_date": "1403-02-15",
      "week_end_date": "1403-02-19",
      "open": 6765.0,
      "high": 6765.0,
      "low": 6468.0,
      "close": 6491.0,
      "weekly_volume": 2738597.0,
      "weekly_trade_value_toman": 1795806453.4,
      "simple_return": -0.027419838178004197,
      "log_return": -0.027802778277850743,
      "rolling_26w_volatility": 0.13820459889326847
    },
    {
      "week_start_date": "1403-02-22",
      "week_end_date": "1403-02-26",
      "open": 6628.0,
      "high": 6628.0,
      "low": 6354.0,
      "close": 6476.0,
      "weekly_volume": 1811310.0,
      "weekly_trade_value_toman": 1173639484.1,
      "simple_return": -0.002310892004313665,
      "log_return": -0.0023135662359428304,
      "rolling_26w_volatility": 0.13216541242311405
    },
    {
      "week_start_date": "1403-02-29",
      "week_end_date": "1403-03-02",
      "open": 6537.0,
      "high": 6590.0,
      "low": 6209.0,
      "close": 6399.0,
      "weekly_volume": 2243012.0,
      "weekly_trade_value_toman": 1402923075.3000002,
      "simple_return": -0.01189005558987029,
      "log_return": -0.01196130765806553,
      "rolling_26w_volatility": 0.11910343009227417
    },
    {
      "week_start_date": "1403-03-05",
      "week_end_date": "1403-03-09",
      "open": 6346.0,
      "high": 6468.0,
      "low": 6087.0,
      "close": 6308.0,
      "weekly_volume": 5110905.0,
      "weekly_trade_value_toman": 3171902377.5,
      "simple_return": -0.0142209720268792,
      "log_return": -0.014323059056531277,
      "rolling_26w_volatility": 0.12091258720659671
    },
    {
      "week_start_date": "1403-03-12",
      "week_end_date": "1403-03-16",
      "open": 6323.0,
      "high": 6323.0,
      "low": 6079.0,
      "close": 6193.0,
      "weekly_volume": 354219.0,
      "weekly_trade_value_toman": 221744376.3,
      "simple_return": -0.018230818008877617,
      "log_return": -0.018399047144868064,
      "rolling_26w_volatility": 0.11485395253452195
    },
    {
      "week_start_date": "1403-03-19",
      "week_end_date": "1403-03-23",
      "open": 6201.0,
      "high": 6308.0,
      "low": 6087.0,
      "close": 6216.0,
      "weekly_volume": 875344.0,
      "weekly_trade_value_toman": 542816728.3,
      "simple_return": 0.003713870498950428,
      "log_return": 0.003706991109422349,
      "rolling_26w_volatility": 0.11352341242150435
    },
    {
      "week_start_date": "1403-03-26",
      "week_end_date": "1403-03-30",
      "open": 6315.0,
      "high": 6315.0,
      "low": 6193.0,
      "close": 6270.0,
      "weekly_volume": 566715.0,
      "weekly_trade_value_toman": 355357480.5,
      "simple_return": 0.008687258687258687,
      "log_return": 0.008649741579482938,
      "rolling_26w_volatility": 0.11410942958826155
    },
    {
      "week_start_date": "1403-04-02",
      "week_end_date": "1403-04-06",
      "open": 6270.0,
      "high": 6354.0,
      "low": 6247.0,
      "close": 6293.0,
      "weekly_volume": 4522571.0,
      "weekly_trade_value_toman": 2843287702.5,
      "simple_return": 0.003668261562998405,
      "log_return": 0.00366154989996717,
      "rolling_26w_volatility": 0.11423731228889801
    },
    {
      "week_start_date": "1403-04-09",
      "week_end_date": "1403-04-13",
      "open": 6254.0,
      "high": 6582.0,
      "low": 6079.0,
      "close": 6254.0,
      "weekly_volume": 3191438.0,
      "weekly_trade_value_toman": 1996218673.4,
      "simple_return": -0.006197362148418878,
      "log_return": -0.006216645509147034,
      "rolling_26w_volatility": 0.11406375141779732
    },
    {
      "week_start_date": "1403-04-16",
      "week_end_date": "1403-04-20",
      "open": 6598.0,
      "high": 6636.0,
      "low": 6079.0,
      "close": 6338.0,
      "weekly_volume": 3037765.0,
      "weekly_trade_value_toman": 1937560392.7,
      "simple_return": 0.013431403901503039,
      "log_return": 0.013342002233079525,
      "rolling_26w_volatility": 0.10879228028223811
    },
    {
      "week_start_date": "1403-04-23",
      "week_end_date": "1403-04-27",
      "open": 6239.0,
      "high": 6392.0,
      "low": 6148.0,
      "close": 6148.0,
      "weekly_volume": 1049972.0,
      "weekly_trade_value_toman": 652629099.7,
      "simple_return": -0.029977911012937834,
      "log_return": -0.030436435592379525,
      "rolling_26w_volatility": 0.1146144503937722
    },
    {
      "week_start_date": "1403-04-30",
      "week_end_date": "1403-05-03",
      "open": 6186.0,
      "high": 6468.0,
      "low": 6071.0,
      "close": 6178.0,
      "weekly_volume": 946611.0,
      "weekly_trade_value_toman": 589300235.5,
      "simple_return": 0.004879635653871178,
      "log_return": 0.00486776882004053,
      "rolling_26w_volatility": 0.11010174812039893
    },
    {
      "week_start_date": "1403-05-06",
      "week_end_date": "1403-05-10",
      "open": 6239.0,
      "high": 6331.0,
      "low": 5881.0,
      "close": 6102.0,
      "weekly_volume": 1759306.0,
      "weekly_trade_value_toman": 1070465478.6999999,
      "simple_return": -0.012301715765619942,
      "log_return": -0.012378008201912013,
      "rolling_26w_volatility": 0.10637024048891211
    },
    {
      "week_start_date": "1403-05-13",
      "week_end_date": "1403-05-17",
      "open": 5987.0,
      "high": 6155.0,
      "low": 5911.0,
      "close": 6071.0,
      "weekly_volume": 1197283.0,
      "weekly_trade_value_toman": 727154186.4,
      "simple_return": -0.0050803015404785315,
      "log_return": -0.005093250146180933,
      "rolling_26w_volatility": 0.10637793518135444
    },
    {
      "week_start_date": "1403-05-20",
      "week_end_date": "1403-05-24",
      "open": 6102.0,
      "high": 6163.0,
      "low": 6071.0,
      "close": 6155.0,
      "weekly_volume": 266644.0,
      "weekly_trade_value_toman": 162726305.0,
      "simple_return": 0.01383627079558557,
      "log_return": 0.013741423488119738,
      "rolling_26w_volatility": 0.10851754278469324
    },
    {
      "week_start_date": "1403-05-27",
      "week_end_date": "1403-05-31",
      "open": 6155.0,
      "high": 6224.0,
      "low": 5980.0,
      "close": 6140.0,
      "weekly_volume": 709977.0,
      "weekly_trade_value_toman": 431875700.2,
      "simple_return": -0.002437043054427295,
      "log_return": -0.0024400174773657113,
      "rolling_26w_volatility": 0.10283565131013035
    },
    {
      "week_start_date": "1403-06-03",
      "week_end_date": "1403-06-07",
      "open": 6041.0,
      "high": 6186.0,
      "low": 5987.0,
      "close": 6117.0,
      "weekly_volume": 1877736.0,
      "weekly_trade_value_toman": 1149844822.1,
      "simple_return": -0.003745928338762215,
      "log_return": -0.003752961898623259,
      "rolling_26w_volatility": 0.10156921227454337
    },
    {
      "week_start_date": "1403-06-10",
      "week_end_date": "1403-06-14",
      "open": 6171.0,
      "high": 6186.0,
      "low": 6148.0,
      "close": 6186.0,
      "weekly_volume": 796501.0,
      "weekly_trade_value_toman": 492342593.09999996,
      "simple_return": 0.011280039234919078,
      "log_return": 0.01121689400245003,
      "rolling_26w_volatility": 0.10343228098389697
    },
    {
      "week_start_date": "1403-06-17",
      "week_end_date": "1403-06-21",
      "open": 6209.0,
      "high": 6224.0,
      "low": 6018.0,
      "close": 6155.0,
      "weekly_volume": 201149.0,
      "weekly_trade_value_toman": 123271928.2,
      "simple_return": -0.005011315874555448,
      "log_return": -0.005023914626461093,
      "rolling_26w_volatility": 0.10318723732564679
    },
    {
      "week_start_date": "1403-06-24",
      "week_end_date": "1403-06-28",
      "open": 6178.0,
      "high": 6270.0,
      "low": 5957.0,
      "close": 6254.0,
      "weekly_volume": 1755556.0,
      "weekly_trade_value_toman": 1094089072.3999999,
      "simple_return": 0.016084484159220147,
      "log_return": 0.0159564993992326,
      "rolling_26w_volatility": 0.10461781894922707
    },
    {
      "week_start_date": "1403-06-31",
      "week_end_date": "1403-07-04",
      "open": 6247.0,
      "high": 6361.0,
      "low": 6079.0,
      "close": 6178.0,
      "weekly_volume": 1004060.0,
      "weekly_trade_value_toman": 623806854.4000001,
      "simple_return": -0.012152222577550368,
      "log_return": -0.012226664539259541,
      "rolling_26w_volatility": 0.10462202669594381
    },
    {
      "week_start_date": "1403-07-07",
      "week_end_date": "1403-07-11",
      "open": 6254.0,
      "high": 6254.0,
      "low": 6125.0,
      "close": 6148.0,
      "weekly_volume": 1408136.0,
      "weekly_trade_value_toman": 868978048.4999999,
      "simple_return": -0.004855940433797346,
      "log_return": -0.004867768820040524,
      "rolling_26w_volatility": 0.09484299790657305
    },
    {
      "week_start_date": "1403-07-14",
      "week_end_date": "1403-07-18",
      "open": 6171.0,
      "high": 6232.0,
      "low": 6110.0,
      "close": 6232.0,
      "weekly_volume": 670319.0,
      "weekly_trade_value_toman": 415013873.9,
      "simple_return": 0.013662979830839297,
      "log_return": 0.013570482892097611,
      "rolling_26w_volatility": 0.09499804778643027
    },
    {
      "week_start_date": "1403-07-21",
      "week_end_date": "1403-07-25",
      "open": 6171.0,
      "high": 6262.0,
      "low": 6071.0,
      "close": 6232.0,
      "weekly_volume": 301013.0,
      "weekly_trade_value_toman": 186690466.7,
      "simple_return": 0.0,
      "log_return": 0.0,
      "rolling_26w_volatility": 0.09266934226236713
    },
    {
      "week_start_date": "1403-07-28",
      "week_end_date": "1403-08-02",
      "open": 6064.0,
      "high": 6132.0,
      "low": 5972.0,
      "close": 6094.0,
      "weekly_volume": 296247.0,
      "weekly_trade_value_toman": 180501929.20000002,
      "simple_return": -0.022143774069319642,
      "log_return": -0.022392628004929863,
      "rolling_26w_volatility": 0.09612522628601729
    },
    {
      "week_start_date": "1403-08-05",
      "week_end_date": "1403-08-09",
      "open": 6254.0,
      "high": 6338.0,
      "low": 5972.0,
      "close": 5987.0,
      "weekly_volume": 3707140.0,
      "weekly_trade_value_toman": 2223695180.2999997,
      "simple_return": -0.017558254020347882,
      "log_return": -0.017714228620302253,
      "rolling_26w_volatility": 0.09397913788688404
    },
    {
      "week_start_date": "1403-08-12",
      "week_end_date": "1403-08-16",
      "open": 6125.0,
      "high": 6125.0,
      "low": 5759.0,
      "close": 5926.0,
      "weekly_volume": 725219.0,
      "weekly_trade_value_toman": 426953088.6,
      "simple_return": -0.010188742274929012,
      "log_return": -0.010241002791841536,
      "rolling_26w_volatility": 0.08788036064245455
    },
    {
      "week_start_date": "1403-08-19",
      "week_end_date": "1403-08-23",
      "open": 5797.0,
      "high": 6110.0,
      "low": 5797.0,
      "close": 5865.0,
      "weekly_volume": 2345164.0,
      "weekly_trade_value_toman": 1392434814.8,
      "simple_return": -0.010293621329733379,
      "log_return": -0.010346967045934661,
      "rolling_26w_volatility": 0.08838717758641
    },
    {
      "week_start_date": "1403-08-26",
      "week_end_date": "1403-08-30",
      "open": 6033.0,
      "high": 6483.0,
      "low": 6033.0,
      "close": 6483.0,
      "weekly_volume": 5856777.0,
      "weekly_trade_value_toman": 3637981957.7999997,
      "simple_return": 0.10537084398976983,
      "log_return": 0.10018088408741982,
      "rolling_26w_volatility": 0.1707690962653169
    },
    {
      "week_start_date": "1403-09-03",
      "week_end_date": "1403-09-07",
      "open": 6483.0,
      "high": 6628.0,
      "low": 6186.0,
      "close": 6499.0,
      "weekly_volume": 23202455.0,
      "weekly_trade_value_toman": 14897048770.8,
      "simple_return": 0.0024679932130186643,
      "log_return": 0.002464952719353267,
      "rolling_26w_volatility": 0.16938250312382497
    },
    {
      "week_start_date": "1403-09-10",
      "week_end_date": "1403-09-14",
      "open": 6544.0,
      "high": 6941.0,
      "low": 6285.0,
      "close": 6941.0,
      "weekly_volume": 33008542.0,
      "weekly_trade_value_toman": 22359296164.4,
      "simple_return": 0.06801046314817664,
      "log_return": 0.06579753744523478,
      "rolling_26w_volatility": 0.1897954259471405
    },
    {
      "week_start_date": "1403-09-17",
      "week_end_date": "1403-09-21",
      "open": 7147.0,
      "high": 7795.0,
      "low": 7147.0,
      "close": 7780.0,
      "weekly_volume": 42382636.0,
      "weekly_trade_value_toman": 31531386766.5,
      "simple_return": 0.12087595447341881,
      "log_return": 0.11411048183285358,
      "rolling_26w_volatility": 0.2451295240153486
    },
    {
      "week_start_date": "1403-09-24",
      "week_end_date": "1403-09-28",
      "open": 7803.0,
      "high": 8215.0,
      "low": 7399.0,
      "close": 7719.0,
      "weekly_volume": 24637831.0,
      "weekly_trade_value_toman": 19099760018.6,
      "simple_return": -0.007840616966580977,
      "log_return": -0.007871516222583454,
      "rolling_26w_volatility": 0.24623801919760757
    },
    {
      "week_start_date": "1403-10-01",
      "week_end_date": "1403-10-05",
      "open": 7826.0,
      "high": 8512.0,
      "low": 7719.0,
      "close": 8276.0,
      "weekly_volume": 17127676.0,
      "weekly_trade_value_toman": 13855751506.1,
      "simple_return": 0.07215960616660189,
      "log_return": 0.06967493791557978,
      "rolling_26w_volatility": 0.2610713641676699
    },
    {
      "week_start_date": "1403-10-08",
      "week_end_date": "1403-10-12",
      "open": 8177.0,
      "high": 8871.0,
      "low": 8161.0,
      "close": 8619.0,
      "weekly_volume": 15311196.0,
      "weekly_trade_value_toman": 12964951181.800001,
      "simple_return": 0.04144514258095698,
      "log_return": 0.04060930878196561,
      "rolling_26w_volatility": 0.2632116169992384
    },
    {
      "week_start_date": "1403-10-15",
      "week_end_date": "1403-10-19",
      "open": 8726.0,
      "high": 8924.0,
      "low": 8665.0,
      "close": 8894.0,
      "weekly_volume": 6091335.0,
      "weekly_trade_value_toman": 5384242542.6,
      "simple_return": 0.03190625362571064,
      "log_return": 0.03140782342324252,
      "rolling_26w_volatility": 0.2645915226999364
    },
    {
      "week_start_date": "1403-10-22",
      "week_end_date": "1403-10-26",
      "open": 9156.0,
      "high": 9331.0,
      "low": 8692.0,
      "close": 9331.0,
      "weekly_volume": 19355072.0,
      "weekly_trade_value_toman": 17655882347.5,
      "simple_return": 0.04913424780751068,
      "log_return": 0.04796529816338028,
      "rolling_26w_volatility": 0.2610082087865322
    },
    {
      "week_start_date": "1403-10-29",
      "week_end_date": "1403-11-03",
      "open": 9576.0,
      "high": 10101.0,
      "low": 9104.0,
      "close": 10093.0,
      "weekly_volume": 9990049.0,
      "weekly_trade_value_toman": 9720085413.7,
      "simple_return": 0.08166327296109742,
      "log_return": 0.07849992400483743,
      "rolling_26w_volatility": 0.274853495701245
    },
    {
      "week_start_date": "1403-11-06",
      "week_end_date": "1403-11-10",
      "open": 10277.0,
      "high": 10355.0,
      "low": 9874.0,
      "close": 10084.0,
      "weekly_volume": 6360598.0,
      "weekly_trade_value_toman": 6436500477.3,
      "simple_return": -0.0008917071237491331,
      "log_return": -0.0008921049310490084,
      "rolling_26w_volatility": 0.2726074204226667
    },
    {
      "week_start_date": "1403-11-13",
      "week_end_date": "1403-11-17",
      "open": 10066.0,
      "high": 10303.0,
      "low": 9751.0,
      "close": 10163.0,
      "weekly_volume": 4327374.0,
      "weekly_trade_value_toman": 4365168817.8,
      "simple_return": 0.007834192780642603,
      "log_return": 0.007803664829956075,
      "rolling_26w_volatility": 0.2708092307497276
    },
    {
      "week_start_date": "1403-11-20",
      "week_end_date": "1403-11-24",
      "open": 9848.0,
      "high": 10242.0,
      "low": 9848.0,
      "close": 9891.0,
      "weekly_volume": 2155967.0,
      "weekly_trade_value_toman": 2151640659.1000004,
      "simple_return": -0.02676375086096625,
      "log_return": -0.02712842139792572,
      "rolling_26w_volatility": 0.2787673086628736
    },
    {
      "week_start_date": "1403-11-27",
      "week_end_date": "1403-12-01",
      "open": 10154.0,
      "high": 10154.0,
      "low": 9594.0,
      "close": 9996.0,
      "weekly_volume": 3587223.0,
      "weekly_trade_value_toman": 3520505509.5,
      "simple_return": 0.010615711252653927,
      "log_return": 0.010559760215002253,
      "rolling_26w_volatility": 0.2773636493442074
    },
    {
      "week_start_date": "1403-12-04",
      "week_end_date": "1403-12-08",
      "open": 9848.0,
      "high": 10136.0,
      "low": 9681.0,
      "close": 9690.0,
      "weekly_volume": 2770660.0,
      "weekly_trade_value_toman": 2702263521.0,
      "simple_return": -0.030612244897959183,
      "log_return": -0.03109058707003112,
      "rolling_26w_volatility": 0.28457655008072397
    },
    {
      "week_start_date": "1403-12-11",
      "week_end_date": "1403-12-15",
      "open": 9629.0,
      "high": 10031.0,
      "low": 9524.0,
      "close": 9804.0,
      "weekly_volume": 2883244.0,
      "weekly_trade_value_toman": 2784110433.7,
      "simple_return": 0.011764705882352941,
      "log_return": 0.011696039763191236,
      "rolling_26w_volatility": 0.28455467521423644
    },
    {
      "week_start_date": "1403-12-18",
      "week_end_date": "1403-12-22",
      "open": 9541.0,
      "high": 9839.0,
      "low": 9357.0,
      "close": 9559.0,
      "weekly_volume": 5977384.0,
      "weekly_trade_value_toman": 5669128784.5,
      "simple_return": -0.02498980008159935,
      "log_return": -0.02530734658424061,
      "rolling_26w_volatility": 0.28933129932562895
    },
    {
      "week_start_date": "1403-12-25",
      "week_end_date": "1403-12-29",
      "open": 9795.0,
      "high": 9874.0,
      "low": 9314.0,
      "close": 9804.0,
      "weekly_volume": 2928145.0,
      "weekly_trade_value_toman": 2863656547.4,
      "simple_return": 0.02563029605607281,
      "log_return": 0.02530734658424061,
      "rolling_26w_volatility": 0.28956787003121787
    },
    {
      "week_start_date": "1404-01-02",
      "week_end_date": "1404-01-06",
      "open": 9734.0,
      "high": 9751.0,
      "low": 9480.0,
      "close": 9743.0,
      "weekly_volume": 405433.0,
      "weekly_trade_value_toman": 394830708.79999995,
      "simple_return": -0.006221950224398204,
      "log_return": -0.006241387222661949,
      "rolling_26w_volatility": 0.28842025295636586
    },
    {
      "week_start_date": "1404-01-09",
      "week_end_date": "1404-01-13",
      "open": 9769.0,
      "high": 9874.0,
      "low": 9576.0,
      "close": 9874.0,
      "weekly_volume": 4093450.0,
      "weekly_trade_value_toman": 4031884657.0,
      "simple_return": 0.013445550651749974,
      "log_return": 0.01335596139346689,
      "rolling_26w_volatility": 0.2866236515560709
    },
    {
      "week_start_date": "1404-01-16",
      "week_end_date": "1404-01-20",
      "open": 10023.0,
      "high": 11108.0,
      "low": 10023.0,
      "close": 11108.0,
      "weekly_volume": 11040531.0,
      "weekly_trade_value_toman": 11745392128.8,
      "simple_return": 0.12497468098035244,
      "log_return": 0.117760529607882,
      "rolling_26w_volatility": 0.3191363907224872
    },
    {
      "week_start_date": "1404-01-23",
      "week_end_date": "1404-01-27",
      "open": 11397.0,
      "high": 12185.0,
      "low": 10968.0,
      "close": 11651.0,
      "weekly_volume": 11881769.0,
      "weekly_trade_value_toman": 13834462094.0,
      "simple_return": 0.048883687432481095,
      "log_return": 0.04772644379325103,
      "rolling_26w_volatility": 0.3193589886052354
    },
    {
      "week_start_date": "1404-01-30",
      "week_end_date": "1404-02-03",
      "open": 11397.0,
      "high": 12412.0,
      "low": 11388.0,
      "close": 11791.0,
      "weekly_volume": 36381845.0,
      "weekly_trade_value_toman": 43305806159.700005,
      "simple_return": 0.012016135953995366,
      "log_return": 0.011944515356732273,
      "rolling_26w_volatility": 0.31258933458256805
    },
    {
      "week_start_date": "1404-02-06",
      "week_end_date": "1404-02-10",
      "open": 12211.0,
      "high": 13419.0,
      "low": 11765.0,
      "close": 13419.0,
      "weekly_volume": 28759631.0,
      "weekly_trade_value_toman": 36828839792.7,
      "simple_return": 0.138071410397761,
      "log_return": 0.1293350845242844,
      "rolling_26w_volatility": 0.338516908399083
    },
    {
      "week_start_date": "1404-02-13",
      "week_end_date": "1404-02-17",
      "open": 13200.0,
      "high": 14076.0,
      "low": 13156.0,
      "close": 13200.0,
      "weekly_volume": 18453055.0,
      "weekly_trade_value_toman": 24824307418.1,
      "simple_return": -0.01632014308070646,
      "log_return": -0.016454783526495625,
      "rolling_26w_volatility": 0.3402029490056641
    },
    {
      "week_start_date": "1404-02-20",
      "week_end_date": "1404-02-24",
      "open": 13314.0,
      "high": 13358.0,
      "low": 12605.0,
      "close": 13200.0,
      "weekly_volume": 36129024.0,
      "weekly_trade_value_toman": 46705113589.2,
      "simple_return": 0.0,
      "log_return": 0.0,
      "rolling_26w_volatility": 0.3379067175401362
    },
    {
      "week_start_date": "1404-02-27",
      "week_end_date": "1404-02-31",
      "open": 13533.0,
      "high": 14286.0,
      "low": 13008.0,
      "close": 14286.0,
      "weekly_volume": 28463879.0,
      "weekly_trade_value_toman": 38956862823.600006,
      "simple_return": 0.08227272727272728,
      "log_return": 0.07906320714045556,
      "rolling_26w_volatility": 0.33017112552267897
    },
    {
      "week_start_date": "1404-03-03",
      "week_end_date": "1404-03-07",
      "open": 14627.0,
      "high": 15940.0,
      "low": 14618.0,
      "close": 14960.0,
      "weekly_volume": 25686287.0,
      "weekly_trade_value_toman": 38618798906.0,
      "simple_return": 0.04717905641887162,
      "log_return": 0.046099935813550486,
      "rolling_26w_volatility": 0.3282564558976314
    },
    {
      "week_start_date": "1404-03-10",
      "week_end_date": "1404-03-14",
      "open": 15161.0,
      "high": 15310.0,
      "low": 14163.0,
      "close": 14303.0,
      "weekly_volume": 11233685.0,
      "weekly_trade_value_toman": 16300838470.3,
      "simple_return": -0.04391711229946524,
      "log_return": -0.044910667073568195,
      "rolling_26w_volatility": 0.34165810711216277
    },
    {
      "week_start_date": "1404-03-17",
      "week_end_date": "1404-03-21",
      "open": 14391.0,
      "high": 14645.0,
      "low": 13778.0,
      "close": 14137.0,
      "weekly_volume": 4463286.0,
      "weekly_trade_value_toman": 6312860530.6,
      "simple_return": -0.01160595679228134,
      "log_return": -0.011673831587867554,
      "rolling_26w_volatility": 0.3212710485535752
    },
    {
      "week_start_date": "1404-03-24",
      "week_end_date": "1404-03-28",
      "open": 14137.0,
      "high": 14137.0,
      "low": 14137.0,
      "close": 14137.0,
      "weekly_volume": 0.0,
      "weekly_trade_value_toman": 0.0,
      "simple_return": 0.0,
      "log_return": 0.0,
      "rolling_26w_volatility": 0.3198891416934076
    },
    {
      "week_start_date": "1404-03-31",
      "week_end_date": "1404-04-04",
      "open": 14137.0,
      "high": 14137.0,
      "low": 14137.0,
      "close": 14137.0,
      "weekly_volume": 0.0,
      "weekly_trade_value_toman": 0.0,
      "simple_return": 0.0,
      "log_return": 0.0,
      "rolling_26w_volatility": 0.3139886957315509
    },
    {
      "week_start_date": "1404-04-07",
      "week_end_date": "1404-04-11",
      "open": 13690.0,
      "high": 13690.0,
      "low": 12692.0,
      "close": 13235.0,
      "weekly_volume": 17529031.0,
      "weekly_trade_value_toman": 23268731258.1,
      "simple_return": -0.0638042017401146,
      "log_return": -0.06593063820583091,
      "rolling_26w_volatility": 0.3352899817665309
    },
    {
      "week_start_date": "1404-04-14",
      "week_end_date": "1404-04-18",
      "open": 12596.0,
      "high": 12736.0,
      "low": 12194.0,
      "close": 12605.0,
      "weekly_volume": 5996128.0,
      "weekly_trade_value_toman": 7533903795.6,
      "simple_return": -0.04760105780128447,
      "log_return": -0.0487712750391814,
      "rolling_26w_volatility": 0.3468471992984926
    },
    {
      "week_start_date": "1404-04-21",
      "week_end_date": "1404-04-25",
      "open": 12386.0,
      "high": 13069.0,
      "low": 12325.0,
      "close": 12868.0,
      "weekly_volume": 9185144.0,
      "weekly_trade_value_toman": 11662499045.2,
      "simple_return": 0.020864736215787386,
      "log_return": 0.02065004873689682,
      "rolling_26w_volatility": 0.3433204113108883
    },
    {
      "week_start_date": "1404-04-28",
      "week_end_date": "1404-05-01",
      "open": 13235.0,
      "high": 14391.0,
      "low": 12561.0,
      "close": 13927.0,
      "weekly_volume": 26627877.0,
      "weekly_trade_value_toman": 36889811468.299995,
      "simple_return": 0.08229717127758782,
      "log_return": 0.07908579269417491,
      "rolling_26w_volatility": 0.3435560864784462
    },
    {
      "week_start_date": "1404-05-04",
      "week_end_date": "1404-05-08",
      "open": 13708.0,
      "high": 13725.0,
      "low": 12824.0,
      "close": 12824.0,
      "weekly_volume": 11020841.0,
      "weekly_trade_value_toman": 14713564946.9,
      "simple_return": -0.07919867882530336,
      "log_return": -0.08251098676370311,
      "rolling_26w_volatility": 0.3685943671949393
    },
    {
      "week_start_date": "1404-05-11",
      "week_end_date": "1404-05-15",
      "open": 12614.0,
      "high": 12622.0,
      "low": 11887.0,
      "close": 12018.0,
      "weekly_volume": 16875536.0,
      "weekly_trade_value_toman": 20898988399.7,
      "simple_return": -0.06285090455396132,
      "log_return": -0.06491288939551566,
      "rolling_26w_volatility": 0.38324037970361585
    },
    {
      "week_start_date": "1404-05-18",
      "week_end_date": "1404-05-22",
      "open": 12159.0,
      "high": 12526.0,
      "low": 11450.0,
      "close": 11450.0,
      "weekly_volume": 5895261.0,
      "weekly_trade_value_toman": 6958175261.9,
      "simple_return": -0.0472624396738226,
      "log_return": -0.04841579591148754,
      "rolling_26w_volatility": 0.38826908507807806
    },
    {
      "week_start_date": "1404-05-25",
      "week_end_date": "1404-05-29",
      "open": 11432.0,
      "high": 12377.0,
      "low": 11432.0,
      "close": 12027.0,
      "weekly_volume": 14219853.0,
      "weekly_trade_value_toman": 16970857338.8,
      "simple_return": 0.05039301310043668,
      "log_return": 0.04916439232823091,
      "rolling_26w_volatility": 0.39309707416790224
    },
    {
      "week_start_date": "1404-06-01",
      "week_end_date": "1404-06-05",
      "open": 11695.0,
      "high": 12386.0,
      "low": 11651.0,
      "close": 11992.0,
      "weekly_volume": 2176533.0,
      "weekly_trade_value_toman": 2591482668.5,
      "simple_return": -0.0029101188991435935,
      "log_return": -0.0029143615281830315,
      "rolling_26w_volatility": 0.3894034001379049
    },
    {
      "week_start_date": "1404-06-08",
      "week_end_date": "1404-06-12",
      "open": 12229.0,
      "high": 12272.0,
      "low": 11590.0,
      "close": 11966.0,
      "weekly_volume": 3382685.0,
      "weekly_trade_value_toman": 4043330922.0,
      "simple_return": -0.0021681120747164776,
      "log_return": -0.0021704658324565025,
      "rolling_26w_volatility": 0.3896380099978082
    },
    {
      "week_start_date": "1404-06-15",
      "week_end_date": "1404-06-19",
      "open": 11966.0,
      "high": 12509.0,
      "low": 11773.0,
      "close": 12176.0,
      "weekly_volume": 12696208.0,
      "weekly_trade_value_toman": 15488783901.7,
      "simple_return": 0.01754972421861942,
      "log_return": 0.01739750615148988,
      "rolling_26w_volatility": 0.38679148718984535
    },
    {
      "week_start_date": "1404-06-22",
      "week_end_date": "1404-06-26",
      "open": 12185.0,
      "high": 12421.0,
      "low": 12071.0,
      "close": 12141.0,
      "weekly_volume": 8793125.0,
      "weekly_trade_value_toman": 10751645381.7,
      "simple_return": -0.002874507227332457,
      "log_return": -0.002878646557491865,
      "rolling_26w_volatility": 0.3864200592943891
    },
    {
      "week_start_date": "1404-06-29",
      "week_end_date": "1404-07-02",
      "open": 11922.0,
      "high": 12404.0,
      "low": 11695.0,
      "close": 11983.0,
      "weekly_volume": 3889932.0,
      "weekly_trade_value_toman": 4653248152.1,
      "simple_return": -0.01301375504488922,
      "log_return": -0.013099175861458656,
      "rolling_26w_volatility": 0.3870751428971631
    },
    {
      "week_start_date": "1404-07-05",
      "week_end_date": "1404-07-09",
      "open": 11975.0,
      "high": 13218.0,
      "low": 11975.0,
      "close": 12596.0,
      "weekly_volume": 18155361.0,
      "weekly_trade_value_toman": 23029235048.799995,
      "simple_return": 0.051155804055745636,
      "log_return": 0.04989032453839862,
      "rolling_26w_volatility": 0.39155701661064574
    },
    {
      "week_start_date": "1404-07-12",
      "week_end_date": "1404-07-16",
      "open": 13121.0,
      "high": 13524.0,
      "low": 12509.0,
      "close": 12544.0,
      "weekly_volume": 28193632.0,
      "weekly_trade_value_toman": 36564210181.8,
      "simple_return": -0.00412829469672912,
      "log_return": -0.004136839630726211,
      "rolling_26w_volatility": 0.3578657670447134
    },
    {
      "week_start_date": "1404-07-19",
      "week_end_date": "1404-07-23",
      "open": 13060.0,
      "high": 13953.0,
      "low": 13043.0,
      "close": 13078.0,
      "weekly_volume": 24657420.0,
      "weekly_trade_value_toman": 32676711683.4,
      "simple_return": 0.04257015306122449,
      "log_return": 0.041688965531032254,
      "rolling_26w_volatility": 0.3564541475709015
    },
    {
      "week_start_date": "1404-07-26",
      "week_end_date": "1404-07-30",
      "open": 13419.0,
      "high": 13918.0,
      "low": 12929.0,
      "close": 13296.0,
      "weekly_volume": 17386682.0,
      "weekly_trade_value_toman": 22881519243.3,
      "simple_return": 0.016669215476372533,
      "log_return": 0.01653180897400821,
      "rolling_26w_volatility": 0.35671386657378734
    },
    {
      "week_start_date": "1404-08-03",
      "week_end_date": "1404-08-07",
      "open": 13594.0,
      "high": 13647.0,
      "low": 12806.0,
      "close": 13095.0,
      "weekly_volume": 2419347.0,
      "weekly_trade_value_toman": 3175457010.7000003,
      "simple_return": -0.015117328519855595,
      "log_return": -0.01523276015341715,
      "rolling_26w_volatility": 0.30666061175766823
    },
    {
      "week_start_date": "1404-08-10",
      "week_end_date": "1404-08-14",
      "open": 13463.0,
      "high": 13463.0,
      "low": 12657.0,
      "close": 12763.0,
      "weekly_volume": 7138209.0,
      "weekly_trade_value_toman": 9278732338.5,
      "simple_return": -0.02535318823978618,
      "log_return": -0.025680117959121503,
      "rolling_26w_volatility": 0.30790641376271327
    },
    {
      "week_start_date": "1404-08-17",
      "week_end_date": "1404-08-21",
      "open": 12579.0,
      "high": 13218.0,
      "low": 12211.0,
      "close": 12780.0,
      "weekly_volume": 10977989.0,
      "weekly_trade_value_toman": 13885869405.400002,
      "simple_return": 0.0013319752409308157,
      "log_return": 0.0013310889488351023,
      "rolling_26w_volatility": 0.30792381090505777
    },
    {
      "week_start_date": "1404-08-24",
      "week_end_date": "1404-08-28",
      "open": 12544.0,
      "high": 13454.0,
      "low": 12447.0,
      "close": 13209.0,
      "weekly_volume": 8690715.0,
      "weekly_trade_value_toman": 11228287492.6,
      "simple_return": 0.033568075117370894,
      "log_return": 0.033016966492337645,
      "rolling_26w_volatility": 0.2892656464901897
    },
    {
      "week_start_date": "1404-09-01",
      "week_end_date": "1404-09-05",
      "open": 12885.0,
      "high": 13402.0,
      "low": 12754.0,
      "close": 13340.0,
      "weekly_volume": 2348257.0,
      "weekly_trade_value_toman": 3078149951.5,
      "simple_return": 0.0099174805057158,
      "log_return": 0.009868625045751226,
      "rolling_26w_volatility": 0.28088674728277424
    },
    {
      "week_start_date": "1404-09-08",
      "week_end_date": "1404-09-12",
      "open": 13367.0,
      "high": 13550.0,
      "low": 13104.0,
      "close": 13340.0,
      "weekly_volume": 4301646.0,
      "weekly_trade_value_toman": 5710588928.3,
      "simple_return": 0.0,
      "log_return": 0.0,
      "rolling_26w_volatility": 0.27452557039342573
    },
    {
      "week_start_date": "1404-09-15",
      "week_end_date": "1404-09-19",
      "open": 13472.0,
      "high": 13717.0,
      "low": 12981.0,
      "close": 13480.0,
      "weekly_volume": 5701993.0,
      "weekly_trade_value_toman": 7651132571.0,
      "simple_return": 0.010494752623688156,
      "log_return": 0.010440064996683422,
      "rolling_26w_volatility": 0.2747999992544398
    },
    {
      "week_start_date": "1404-09-22",
      "week_end_date": "1404-09-26",
      "open": 13673.0,
      "high": 13935.0,
      "low": 12999.0,
      "close": 13725.0,
      "weekly_volume": 14509758.0,
      "weekly_trade_value_toman": 19549930701.6,
      "simple_return": 0.01817507418397626,
      "log_return": 0.01801188191143344,
      "rolling_26w_volatility": 0.27622642947723464
    },
    {
      "week_start_date": "1404-09-29",
      "week_end_date": "1404-10-03",
      "open": 13927.0,
      "high": 15844.0,
      "low": 13918.0,
      "close": 15844.0,
      "weekly_volume": 50150595.0,
      "weekly_trade_value_toman": 74659610490.3,
      "simple_return": 0.15438979963570126,
      "log_return": 0.14357189236407591,
      "rolling_26w_volatility": 0.34381133378250517
    },
    {
      "week_start_date": "1404-10-06",
      "week_end_date": "1404-10-10",
      "open": 16290.0,
      "high": 16623.0,
      "low": 15669.0,
      "close": 15669.0,
      "weekly_volume": 16875475.0,
      "weekly_trade_value_toman": 26679270410.699997,
      "simple_return": -0.011045190608432214,
      "log_return": -0.011106641637398858,
      "rolling_26w_volatility": 0.3289087528997254
    },
    {
      "week_start_date": "1404-10-13",
      "week_end_date": "1404-10-17",
      "open": 16340.0,
      "high": 16340.0,
      "low": 14580.0,
      "close": 14580.0,
      "weekly_volume": 57695914.0,
      "weekly_trade_value_toman": 87248046327.0,
      "simple_return": -0.06950028719126938,
      "log_return": -0.07203351154175934,
      "rolling_26w_volatility": 0.3385427743938532
    },
    {
      "week_start_date": "1404-10-20",
      "week_end_date": "1404-10-24",
      "open": 14200.0,
      "high": 14420.0,
      "low": 13260.0,
      "close": 13440.0,
      "weekly_volume": 39549124.0,
      "weekly_trade_value_toman": 55449258354.0,
      "simple_return": -0.07818930041152264,
      "log_return": -0.08141539148550858,
      "rolling_26w_volatility": 0.3592423763906228
    },
    {
      "week_start_date": "1404-10-27",
      "week_end_date": "1404-11-01",
      "open": 13350.0,
      "high": 14030.0,
      "low": 13160.0,
      "close": 13780.0,
      "weekly_volume": 13694047.0,
      "weekly_trade_value_toman": 18519967127.0,
      "simple_return": 0.025297619047619048,
      "log_return": 0.024982930490509047,
      "rolling_26w_volatility": 0.3427625050531318
    },
    {
      "week_start_date": "1404-11-04",
      "week_end_date": "1404-11-08",
      "open": 13830.0,
      "high": 13830.0,
      "low": 11870.0,
      "close": 11990.0,
      "weekly_volume": 15043967.0,
      "weekly_trade_value_toman": 19242630631.0,
      "simple_return": -0.12989840348330914,
      "log_return": -0.13914529654608965,
      "rolling_26w_volatility": 0.3784763610077798
    },
    {
      "week_start_date": "1404-11-11",
      "week_end_date": "1404-11-15",
      "open": 12290.0,
      "high": 12290.0,
      "low": 11320.0,
      "close": 11900.0,
      "weekly_volume": 5085371.0,
      "weekly_trade_value_toman": 6027485275.0,
      "simple_return": -0.007506255212677231,
      "log_return": -0.00753456892193917,
      "rolling_26w_volatility": 0.36735805829100865
    },
    {
      "week_start_date": "1404-11-18",
      "week_end_date": "1404-11-22",
      "open": 12140.0,
      "high": 12500.0,
      "low": 11140.0,
      "close": 11300.0,
      "weekly_volume": 5048055.0,
      "weekly_trade_value_toman": 5813429039.0,
      "simple_return": -0.05042016806722689,
      "log_return": -0.051735674399188865,
      "rolling_26w_volatility": 0.3682898324947846
    },
    {
      "week_start_date": "1404-11-25",
      "week_end_date": "1404-11-29",
      "open": 11400.0,
      "high": 11480.0,
      "low": 10300.0,
      "close": 10400.0,
      "weekly_volume": 9842931.0,
      "weekly_trade_value_toman": 10547334305.0,
      "simple_return": -0.07964601769911504,
      "log_return": -0.08299691957096791,
      "rolling_26w_volatility": 0.3784991840276642
    }
  ]
}